README.rst
setup.py
bin/copy-coverage-html
bin/opsspace-test
cmstoolbox/__init__.py
cmstoolbox/_loadtestpath.py
cmstoolbox/checkexists.py
cmstoolbox/emailtools.py
cmstoolbox/samstatus.py
cmstoolbox/simplefiletools.py
cmstoolbox/siteinfo.py
cmstoolbox/sitereadiness.py
cmstoolbox/webtools.py
cmstoolbox.egg-info/PKG-INFO
cmstoolbox.egg-info/SOURCES.txt
cmstoolbox.egg-info/dependency_links.txt
cmstoolbox.egg-info/requires.txt
cmstoolbox.egg-info/top_level.txt
cmstoolbox/unmergedcleaner/__init__.py
cmstoolbox/unmergedcleaner/_config.py
cmstoolbox/unmergedcleaner/configtools.py
cmstoolbox/unmergedcleaner/listdeletable.py
test/test_example.py
test/test_siteinfo.py
test/test_sitereadiness.py
test/test_unmerged_cleaner.py