Metadata-Version: 1.0
Name: cmstoolbox
Version: 0.17.0
Summary: Tools used by CMS Computing Operations
Home-page: https://github.com/CMSCompOps/OpsSpace
Author: Daniel Abercrombie
Author-email: dabercro@mit.edu
License: UNKNOWN
Platform: UNKNOWN
